{
  "imageName": "design_www.sketch.com_1729629661.png",
  "imageDimensions": {
    "width": 0,
    "height": 0
  },
  "annotations": [
    {
      "id": "prediction-1753109066309-0",
      "x": 279,
      "y": 30,
      "width": 90,
      "height": 24,
      "tag": "dropdown",
      "source": "prediction"
    },
    {
      "id": "prediction-1753109066309-1",
      "x": 399,
      "y": 30,
      "width": 70,
      "height": 24,
      "tag": "dropdown",
      "source": "prediction"
    },
    {
      "id": "prediction-1753109066309-2",
      "x": 499,
      "y": 30,
      "width": 70,
      "height": 24,
      "tag": "button",
      "source": "prediction"
    },
    {
      "id": "prediction-1753109066309-3",
      "x": 599,
      "y": 30,
      "width": 60,
      "height": 24,
      "tag": "dropdown",
      "source": "prediction"
    },
    {
      "id": "prediction-1753109066309-4",
      "x": 1390,
      "y": 24,
      "width": 70,
      "height": 36,
      "tag": "button",
      "source": "prediction"
    },
    {
      "id": "prediction-1753109066309-5",
      "x": 1480,
      "y": 24,
      "width": 140,
      "height": 36,
      "tag": "button",
      "source": "prediction"
    },
    {
      "id": "prediction-1753109066309-6",
      "x": 550,
      "y": 350,
      "width": 200,
      "height": 50,
      "tag": "button",
      "source": "prediction"
    },
    {
      "id": "prediction-1753109066309-7",
      "x": 610,
      "y": 630,
      "width": 100,
      "height": 20,
      "tag": "button",
      "source": "prediction"
    },
    {
      "id": "prediction-1753109066309-8",
      "x": 100,
      "y": 820,
      "width": 150,
      "height": 24,
      "tag": "input",
      "source": "prediction"
    },
    {
      "id": "prediction-1753109066309-9",
      "x": 100,
      "y": 860,
      "width": 150,
      "height": 24,
      "tag": "dropdown",
      "source": "prediction"
    },
    {
      "id": "prediction-1753109066309-10",
      "x": 100,
      "y": 890,
      "width": 150,
      "height": 24,
      "tag": "button",
      "source": "prediction"
    },
    {
      "id": "prediction-1753109066309-11",
      "x": 100,
      "y": 920,
      "width": 150,
      "height": 24,
      "tag": "button",
      "source": "prediction"
    },
    {
      "id": "prediction-1753109066309-12",
      "x": 100,
      "y": 950,
      "width": 150,
      "height": 24,
      "tag": "button",
      "source": "prediction"
    },
    {
      "id": "prediction-1753109066309-13",
      "x": 100,
      "y": 980,
      "width": 150,
      "height": 24,
      "tag": "button",
      "source": "prediction"
    },
    {
      "id": "prediction-1753109066309-14",
      "x": 290,
      "y": 779,
      "width": 30,
      "height": 30,
      "tag": "button",
      "source": "prediction"
    },
    {
      "id": "prediction-1753109066309-15",
      "x": 390,
      "y": 779,
      "width": 30,
      "height": 30,
      "tag": "button",
      "source": "prediction"
    },
    {
      "id": "prediction-1753109066309-16",
      "x": 480,
      "y": 779,
      "width": 30,
      "height": 30,
      "tag": "button",
      "source": "prediction"
    },
    {
      "id": "prediction-1753109066309-17",
      "x": 570,
      "y": 779,
      "width": 30,
      "height": 30,
      "tag": "button",
      "source": "prediction"
    },
    {
      "id": "prediction-1753109066309-18",
      "x": 780,
      "y": 779,
      "width": 80,
      "height": 30,
      "tag": "dropdown",
      "source": "prediction"
    },
    {
      "id": "prediction-1753109066309-19",
      "x": 880,
      "y": 779,
      "width": 30,
      "height": 30,
      "tag": "button",
      "source": "prediction"
    }
  ],
  "metadata": {
    "totalAnnotations": 20,
    "exportedAt": "2025-07-21T15:21:31.419Z"
  }
}